stubwheel/__main__.py
stubwheel-1.0.7.dist-info/LICENSE
stubwheel-1.0.7.dist-info/METADATA
stubwheel-1.0.7.dist-info/WHEEL
stubwheel-1.0.7.dist-info/entry_points.txt
stubwheel-1.0.7.dist-info/top_level.txt
stubwheel-1.0.7.dist-info/RECORD
