Metadata-Version: 2.1
Name: stubwheel
Version: 1.0.7
Summary: a script that reserves a project name on PyPi
Home-page: https://github.com/AlyShmahell/stubwheel
Author: AlyShmahell
Author-email: 
License-File: LICENSE
Requires-Dist: twine >=3.2.0
Requires-Dist: wheel >=0.43.0
